[
  {
    "name": "polygon",
    "chainId": "137",
    "contracts": [
      {
        "name": "AgentRegistry",
        "artifact": "abis/0.8.21/AgentRegistry.json",
        "address": ""
      },
      {
        "name": "AgentFactory",
        "artifact": "abis/0.8.21/AgentFactory.json",
        "address": ""
      },
      {
        "name": "AgentMech",
        "artifact": "abis/0.8.21/AgentMech.json",
        "address": ""
      },
      {
        "name": "AgentFactorySubscription",
        "artifact": "abis/0.8.21/AgentFactorySubscription.json",
        "address": ""
      },
      {
        "name": "AgentMechSubscription",
        "artifact": "abis/0.8.21/AgentMech.json",
        "address": ""
      }
    ]
  },
  {
    "name": "polygonMumbai",
    "chainId": "80001",
    "contracts": [
      {
        "name": "AgentRegistry",
        "artifact": "abis/0.8.21/AgentRegistry.json",
        "address": ""
      },
      {
        "name": "AgentFactory",
        "artifact": "abis/0.8.21/AgentFactory.json",
        "address": ""
      },
      {
        "name": "AgentMech",
        "artifact": "abis/0.8.21/AgentMech.json",
        "address": ""
      },
      {
        "name": "AgentFactorySubscription",
        "artifact": "abis/0.8.21/AgentFactorySubscription.json",
        "address": ""
      },
      {
        "name": "AgentMechSubscription",
        "artifact": "abis/0.8.21/AgentMech.json",
        "address": ""
      }
    ]
  },
  {
    "name": "gnosis",
    "chainId": "100",
    "contracts": [
      {
        "name": "AgentRegistry",
        "artifact": "abis/0.8.21/AgentRegistry.json",
        "address": "0xE49CB081e8d96920C38aA7AB90cb0294ab4Bc8EA"
      },
      {
        "name": "AgentFactory",
        "artifact": "abis/0.8.21/AgentFactory.json",
        "address": "0x4be7A91e67be963806FeFA9C1FD6C53DfC358d94"
      },
      {
        "name": "AgentMech",
        "artifact": "abis/0.8.21/AgentMech.json",
        "address": "0x77af31de935740567cf4ff1986d04b2c964a786a"
      },
      {
        "name": "AgentFactorySubscription",
        "artifact": "abis/0.8.21/AgentFactorySubscription.json",
        "address": "0x910Ca843Cad6C050Faf3f84387879b2928D40370"
      },
      {
        "name": "AgentMechSubscription",
        "artifact": "abis/0.8.21/AgentMech.json",
        "address": "0x327E26bDF1CfEa50BFAe35643B23D5268E41F7F9"
      }
    ]
  },
  {
    "name": "chiado",
    "chainId": "10200",
    "contracts": [
      {
        "name": "AgentRegistry",
        "artifact": "abis/0.8.21/AgentRegistry.json",
        "address": "0x9dEc6B62c197268242A768dc3b153AE7a2701396"
      },
      {
        "name": "AgentFactory",
        "artifact": "abis/0.8.21/AgentFactory.json",
        "address": "0x1d333b46dB6e8FFd271b6C2D2B254868BD9A2dbd"
      },
      {
        "name": "AgentMech",
        "artifact": "abis/0.8.21/AgentMech.json",
        "address": "0x0A3cFc6BEe9658Eda040e6BB366FE963DdCe82C9"
      },
      {
        "name": "AgentFactorySubscription",
        "artifact": "abis/0.8.21/AgentFactorySubscription.json",
        "address": ""
      },
      {
        "name": "AgentMechSubscription",
        "artifact": "abis/0.8.21/AgentMech.json",
        "address": ""
      }
    ]
  },
  {
    "name": "arbitrumOne",
    "chainId": "42161",
    "contracts": [
      {
        "name": "AgentRegistry",
        "artifact": "abis/0.8.21/AgentRegistry.json",
        "address": ""
      },
      {
        "name": "AgentFactory",
        "artifact": "abis/0.8.21/AgentFactory.json",
        "address": ""
      },
      {
        "name": "AgentMech",
        "artifact": "abis/0.8.21/AgentMech.json",
        "address": ""
      },
      {
        "name": "AgentFactorySubscription",
        "artifact": "abis/0.8.21/AgentFactorySubscription.json",
        "address": ""
      },
      {
        "name": "AgentMechSubscription",
        "artifact": "abis/0.8.21/AgentMech.json",
        "address": ""
      }
    ]
  },
  {
    "name": "arbitrumSepolia",
    "chainId": "421614",
    "contracts": [
      {
        "name": "AgentRegistry",
        "artifact": "abis/0.8.21/AgentRegistry.json",
        "address": ""
      },
      {
        "name": "AgentFactory",
        "artifact": "abis/0.8.21/AgentFactory.json",
        "address": ""
      },
      {
        "name": "AgentMech",
        "artifact": "abis/0.8.21/AgentMech.json",
        "address": ""
      },
      {
        "name": "AgentFactorySubscription",
        "artifact": "abis/0.8.21/AgentFactorySubscription.json",
        "address": ""
      },
      {
        "name": "AgentMechSubscription",
        "artifact": "abis/0.8.21/AgentMech.json",
        "address": ""
      }
    ]
  }
]